{
    "Item":
    {
        "Name": "Imperial Standard",
        "id": 1601,
        "Description": "The Empire's emblematic phrase sewn gold on red.",
        "Users":
        {
            "id": [1]
        },
        "canSell": false,
        "Effects":
        {
            "passive": 54,
            "active": 55
           },
        "Types":
        {
            "id": 262144,
            "Type": "Standard"
        },
        "Subtype": 0,
        "Handedness": 0,
        "Stats":
        {
            "Attack": [4,0,0],
            "Protection": [1,1],
            "hit": 0,
            "dodge": 0,
            "crit": 0,
            "favor": 0,
            "wgt": 8,
            "prof": 4,
            "Range": [0,1],
            "uses": 10,
            "price": 0,
            "AP": 0
        },
        "Effective": 0
    }
}